django_modulith/apps.py
django_modulith/interface_decorator.py
django_modulith/interface_registry.py
django_modulith/management/__init__.py
django_modulith/management/commands/__init__.py
django_modulith/management/commands/generatestubs.py
django_modulith/management/commands/modulith.py
django_modulith-0.1.1.dist-info/LICENSE
django_modulith-0.1.1.dist-info/METADATA
django_modulith-0.1.1.dist-info/WHEEL
django_modulith-0.1.1.dist-info/RECORD
