Metadata-Version: 2.3
Name: django-modulith
Version: 0.1.1
Summary: 
License: MIT
Author: Plamen Tarkalanov
Author-email: plamen.tarkalanov@gmail.com
Requires-Python: >=3.10
Classifier: License :: OSI Approved :: MIT License
Classifier: Programming Language :: Python :: 3
Classifier: Programming Language :: Python :: 3.10
Classifier: Programming Language :: Python :: 3.11
Classifier: Programming Language :: Python :: 3.12
Classifier: Programming Language :: Python :: 3.13
Requires-Dist: django (>=5.1.7,<6.0.0)
